{
  "eraId": "senior-civilization-origin",
  "eraName": "中华文明起源与早期国家",
  "playerRole": "殷商铸铜匠",
  "acts": [
    {
      "id": "act-1",
      "title": "殷都铸造",
      "isKeyAct": true,
      "sceneDescription": "清晨的第一缕阳光洒在脸上，你深吸一口气。在商都殷墟的王室铸铜作坊工作新的一天充满了未知与挑战。你作为殷商铸铜匠，深知此刻的重要性，不由得打起十二分精神。",
      "npcDialogues": [
        {
          "speaker": "同伴",
          "text": "今日拜访几位友人。",
          "avatar": "友"
        },
        {
          "speaker": "邻居",
          "text": "备好了茶点。",
          "avatar": "邻"
        }
      ],
      "dialogues": [
        {
          "id": "d-1-1",
          "text": "详查资料考究",
          "speaker": "你",
          "avatar": "你",
          "score": 90,
          "triggeredEvent": "殷都铸造进展顺利",
          "historicalNote": "与中华文明起源与早期国家相关的关键历史事件相关的考古发现与文献记载为后人了解这一时期提供了宝贵的资料。",
          "consequence": "事情发展顺利，达成了预期目标，获得了积极的成果"
        },
        {
          "id": "d-1-2",
          "text": "大胆挥毫创作",
          "speaker": "你",
          "avatar": "你",
          "score": 60,
          "triggeredEvent": "殷都铸造遇到波折",
          "historicalNote": "与中华文明起源与早期国家相关的关键历史事件相关的考古发现与文献记载为后人了解这一时期提供了宝贵的资料。",
          "consequence": "遇到了一些意料之外的困难，需要调整策略继续前进"
        },
        {
          "id": "d-1-3",
          "text": "与友人切磋琢磨",
          "speaker": "你",
          "avatar": "你",
          "score": 75,
          "triggeredEvent": "殷都铸造取得进展",
          "historicalNote": "与中华文明起源与早期国家相关的关键历史事件相关的考古发现与文献记载为后人了解这一时期提供了宝贵的资料。",
          "consequence": "取得了阶段性的进展，整体形势向好发展"
        },
        {
          "id": "d-1-4",
          "text": "低调行事避险",
          "speaker": "你",
          "avatar": "你",
          "score": 55,
          "triggeredEvent": "殷都铸造遭遇困境",
          "historicalNote": "与中华文明起源与早期国家相关的关键历史事件相关的考古发现与文献记载为后人了解这一时期提供了宝贵的资料。",
          "consequence": "遭遇了挫折，损失有限，仍有挽回的余地"
        },
        {
          "id": "d-1-5",
          "text": "另辟蹊径创新",
          "speaker": "你",
          "avatar": "你",
          "score": 85,
          "triggeredEvent": "殷都铸造获得突破",
          "historicalNote": "与中华文明起源与早期国家相关的关键历史事件相关的考古发现与文献记载为后人了解这一时期提供了宝贵的资料。",
          "consequence": "获得了超出预期的突破性进展，令人振奋"
        },
        {
          "id": "d-1-6",
          "text": "坚守气节原则",
          "speaker": "你",
          "avatar": "你",
          "score": 70,
          "triggeredEvent": "殷都铸造平稳推进",
          "historicalNote": "与中华文明起源与早期国家相关的关键历史事件相关的考古发现与文献记载为后人了解这一时期提供了宝贵的资料。",
          "consequence": "稳步推进，虽无重大惊喜，但一切尽在掌握"
        }
      ],
      "nextActId": "act-2"
    },
    {
      "id": "act-2",
      "title": "模范制作",
      "isKeyAct": false,
      "sceneDescription": "阳光透过树叶的缝隙洒落下来，你注意到一处特别之处。精心制作青铜器的陶范和型芯心中涌起一阵好奇与兴奋。你作为殷商铸铜匠，深知此刻的重要性，不由得打起十二分精神。",
      "npcDialogues": [
        {
          "speaker": "长者",
          "text": "这批丝绸成色极好！",
          "avatar": "长"
        },
        {
          "speaker": "友人",
          "text": "定然能卖个好价钱。",
          "avatar": "人"
        }
      ],
      "dialogues": [
        {
          "id": "d-2-1",
          "text": "多方打听确认",
          "speaker": "你",
          "avatar": "你",
          "score": 90,
          "triggeredEvent": "模范制作进展顺利",
          "historicalNote": "殷商铸铜匠在这一时期的生活与经历相关的考古发现与文献记载为后人了解这一时期提供了宝贵的资料。",
          "consequence": "事情发展顺利，达成了预期目标，获得了积极的成果"
        },
        {
          "id": "d-2-2",
          "text": "果断投资决策",
          "speaker": "你",
          "avatar": "你",
          "score": 60,
          "triggeredEvent": "模范制作遇到波折",
          "historicalNote": "殷商铸铜匠在这一时期的生活与经历相关的考古发现与文献记载为后人了解这一时期提供了宝贵的资料。",
          "consequence": "遇到了一些意料之外的困难，需要调整策略继续前进"
        },
        {
          "id": "d-2-3",
          "text": "寻求师长指点",
          "speaker": "你",
          "avatar": "你",
          "score": 75,
          "triggeredEvent": "模范制作取得进展",
          "historicalNote": "殷商铸铜匠在这一时期的生活与经历相关的考古发现与文献记载为后人了解这一时期提供了宝贵的资料。",
          "consequence": "取得了阶段性的进展，整体形势向好发展"
        },
        {
          "id": "d-2-4",
          "text": "稳扎稳打经营",
          "speaker": "你",
          "avatar": "你",
          "score": 55,
          "triggeredEvent": "模范制作遭遇困境",
          "historicalNote": "殷商铸铜匠在这一时期的生活与经历相关的考古发现与文献记载为后人了解这一时期提供了宝贵的资料。",
          "consequence": "遭遇了挫折，损失有限，仍有挽回的余地"
        },
        {
          "id": "d-2-5",
          "text": "改良经营方式",
          "speaker": "你",
          "avatar": "你",
          "score": 85,
          "triggeredEvent": "模范制作获得突破",
          "historicalNote": "殷商铸铜匠在这一时期的生活与经历相关的考古发现与文献记载为后人了解这一时期提供了宝贵的资料。",
          "consequence": "获得了超出预期的突破性进展，令人振奋"
        },
        {
          "id": "d-2-6",
          "text": "诚信童叟无欺",
          "speaker": "你",
          "avatar": "你",
          "score": 70,
          "triggeredEvent": "模范制作平稳推进",
          "historicalNote": "殷商铸铜匠在这一时期的生活与经历相关的考古发现与文献记载为后人了解这一时期提供了宝贵的资料。",
          "consequence": "稳步推进，虽无重大惊喜，但一切尽在掌握"
        }
      ],
      "nextActId": "act-3"
    },
    {
      "id": "act-3",
      "title": "合金熔炼",
      "isKeyAct": false,
      "sceneDescription": "气氛骤然紧张起来。在高温炉中熔炼铜锡合金危险迫在眉睫，容不得半点犹豫，你必须当机立断。你作为殷商铸铜匠，深知此刻的重要性，不由得打起十二分精神。",
      "npcDialogues": [
        {
          "speaker": "邻居",
          "text": "有盗匪！",
          "avatar": "邻"
        },
        {
          "speaker": "同伴",
          "text": "快走！保住货物要紧！",
          "avatar": "友"
        }
      ],
      "dialogues": [
        {
          "id": "d-3-1",
          "text": "审慎评估形势",
          "speaker": "你",
          "avatar": "你",
          "score": 90,
          "triggeredEvent": "合金熔炼进展顺利",
          "historicalNote": "该时代的政治、经济与文化背景相关的考古发现与文献记载为后人了解这一时期提供了宝贵的资料。",
          "consequence": "事情发展顺利，达成了预期目标，获得了积极的成果"
        },
        {
          "id": "d-3-2",
          "text": "勇敢开拓新路",
          "speaker": "你",
          "avatar": "你",
          "score": 60,
          "triggeredEvent": "合金熔炼遇到波折",
          "historicalNote": "该时代的政治、经济与文化背景相关的考古发现与文献记载为后人了解这一时期提供了宝贵的资料。",
          "consequence": "遇到了一些意料之外的困难，需要调整策略继续前进"
        },
        {
          "id": "d-3-3",
          "text": "联络同行合作",
          "speaker": "你",
          "avatar": "你",
          "score": 75,
          "triggeredEvent": "合金熔炼取得进展",
          "historicalNote": "该时代的政治、经济与文化背景相关的考古发现与文献记载为后人了解这一时期提供了宝贵的资料。",
          "consequence": "取得了阶段性的进展，整体形势向好发展"
        },
        {
          "id": "d-3-4",
          "text": "含蓄委婉表达",
          "speaker": "你",
          "avatar": "你",
          "score": 55,
          "triggeredEvent": "合金熔炼遭遇困境",
          "historicalNote": "该时代的政治、经济与文化背景相关的考古发现与文献记载为后人了解这一时期提供了宝贵的资料。",
          "consequence": "遭遇了挫折，损失有限，仍有挽回的余地"
        },
        {
          "id": "d-3-5",
          "text": "开创独特风格",
          "speaker": "你",
          "avatar": "你",
          "score": 85,
          "triggeredEvent": "合金熔炼获得突破",
          "historicalNote": "该时代的政治、经济与文化背景相关的考古发现与文献记载为后人了解这一时期提供了宝贵的资料。",
          "consequence": "获得了超出预期的突破性进展，令人振奋"
        },
        {
          "id": "d-3-6",
          "text": "不为利益所动",
          "speaker": "你",
          "avatar": "你",
          "score": 70,
          "triggeredEvent": "合金熔炼平稳推进",
          "historicalNote": "该时代的政治、经济与文化背景相关的考古发现与文献记载为后人了解这一时期提供了宝贵的资料。",
          "consequence": "稳步推进，虽无重大惊喜，但一切尽在掌握"
        }
      ],
      "nextActId": "act-4"
    },
    {
      "id": "act-4",
      "title": "大型器物",
      "isKeyAct": true,
      "sceneDescription": "历史性的时刻就在眼前。参与铸造大型礼器如司母戊鼎你整理思绪，准备迎接这个重要的转折点。你作为殷商铸铜匠，深知此刻的重要性，不由得打起十二分精神。",
      "npcDialogues": [
        {
          "speaker": "友人",
          "text": "这首诗还得再斟酌斟酌。",
          "avatar": "人"
        },
        {
          "speaker": "长者",
          "text": "腹稿都有了，就缺个好题目。",
          "avatar": "长"
        }
      ],
      "dialogues": [
        {
          "id": "d-4-1",
          "text": "详查资料考究",
          "speaker": "你",
          "avatar": "你",
          "score": 90,
          "triggeredEvent": "大型器物进展顺利",
          "historicalNote": "历史对后世的深远影响相关的考古发现与文献记载为后人了解这一时期提供了宝贵的资料。",
          "consequence": "事情发展顺利，达成了预期目标，获得了积极的成果"
        },
        {
          "id": "d-4-2",
          "text": "大胆挥毫创作",
          "speaker": "你",
          "avatar": "你",
          "score": 60,
          "triggeredEvent": "大型器物遇到波折",
          "historicalNote": "历史对后世的深远影响相关的考古发现与文献记载为后人了解这一时期提供了宝贵的资料。",
          "consequence": "遇到了一些意料之外的困难，需要调整策略继续前进"
        },
        {
          "id": "d-4-3",
          "text": "与友人切磋琢磨",
          "speaker": "你",
          "avatar": "你",
          "score": 75,
          "triggeredEvent": "大型器物取得进展",
          "historicalNote": "历史对后世的深远影响相关的考古发现与文献记载为后人了解这一时期提供了宝贵的资料。",
          "consequence": "取得了阶段性的进展，整体形势向好发展"
        },
        {
          "id": "d-4-4",
          "text": "低调行事避险",
          "speaker": "你",
          "avatar": "你",
          "score": 55,
          "triggeredEvent": "大型器物遭遇困境",
          "historicalNote": "历史对后世的深远影响相关的考古发现与文献记载为后人了解这一时期提供了宝贵的资料。",
          "consequence": "遭遇了挫折，损失有限，仍有挽回的余地"
        },
        {
          "id": "d-4-5",
          "text": "另辟蹊径创新",
          "speaker": "你",
          "avatar": "你",
          "score": 85,
          "triggeredEvent": "大型器物获得突破",
          "historicalNote": "历史对后世的深远影响相关的考古发现与文献记载为后人了解这一时期提供了宝贵的资料。",
          "consequence": "获得了超出预期的突破性进展，令人振奋"
        },
        {
          "id": "d-4-6",
          "text": "坚守气节原则",
          "speaker": "你",
          "avatar": "你",
          "score": 70,
          "triggeredEvent": "大型器物平稳推进",
          "historicalNote": "历史对后世的深远影响相关的考古发现与文献记载为后人了解这一时期提供了宝贵的资料。",
          "consequence": "稳步推进，虽无重大惊喜，但一切尽在掌握"
        }
      ],
      "nextActId": "act-5"
    },
    {
      "id": "act-5",
      "title": "纹饰雕刻",
      "isKeyAct": false,
      "sceneDescription": "日复一日的生活中，这一天似乎有些不同。在铸成的青铜器上精细雕刻纹饰平凡中孕育着变化，你敏锐地察觉到了。你作为殷商铸铜匠，深知此刻的重要性，不由得打起十二分精神。",
      "npcDialogues": [
        {
          "speaker": "同伴",
          "text": "今日行情如何？",
          "avatar": "友"
        },
        {
          "speaker": "邻居",
          "text": "比昨日涨了三成。",
          "avatar": "邻"
        }
      ],
      "dialogues": [
        {
          "id": "d-5-1",
          "text": "多方打听确认",
          "speaker": "你",
          "avatar": "你",
          "score": 90,
          "triggeredEvent": "纹饰雕刻进展顺利",
          "historicalNote": "与中华文明起源与早期国家相关的关键历史事件相关的考古发现与文献记载为后人了解这一时期提供了宝贵的资料。",
          "consequence": "事情发展顺利，达成了预期目标，获得了积极的成果"
        },
        {
          "id": "d-5-2",
          "text": "果断投资决策",
          "speaker": "你",
          "avatar": "你",
          "score": 60,
          "triggeredEvent": "纹饰雕刻遇到波折",
          "historicalNote": "与中华文明起源与早期国家相关的关键历史事件相关的考古发现与文献记载为后人了解这一时期提供了宝贵的资料。",
          "consequence": "遇到了一些意料之外的困难，需要调整策略继续前进"
        },
        {
          "id": "d-5-3",
          "text": "寻求师长指点",
          "speaker": "你",
          "avatar": "你",
          "score": 75,
          "triggeredEvent": "纹饰雕刻取得进展",
          "historicalNote": "与中华文明起源与早期国家相关的关键历史事件相关的考古发现与文献记载为后人了解这一时期提供了宝贵的资料。",
          "consequence": "取得了阶段性的进展，整体形势向好发展"
        },
        {
          "id": "d-5-4",
          "text": "稳扎稳打经营",
          "speaker": "你",
          "avatar": "你",
          "score": 55,
          "triggeredEvent": "纹饰雕刻遭遇困境",
          "historicalNote": "与中华文明起源与早期国家相关的关键历史事件相关的考古发现与文献记载为后人了解这一时期提供了宝贵的资料。",
          "consequence": "遭遇了挫折，损失有限，仍有挽回的余地"
        },
        {
          "id": "d-5-5",
          "text": "改良经营方式",
          "speaker": "你",
          "avatar": "你",
          "score": 85,
          "triggeredEvent": "纹饰雕刻获得突破",
          "historicalNote": "与中华文明起源与早期国家相关的关键历史事件相关的考古发现与文献记载为后人了解这一时期提供了宝贵的资料。",
          "consequence": "获得了超出预期的突破性进展，令人振奋"
        },
        {
          "id": "d-5-6",
          "text": "诚信童叟无欺",
          "speaker": "你",
          "avatar": "你",
          "score": 70,
          "triggeredEvent": "纹饰雕刻平稳推进",
          "historicalNote": "与中华文明起源与早期国家相关的关键历史事件相关的考古发现与文献记载为后人了解这一时期提供了宝贵的资料。",
          "consequence": "稳步推进，虽无重大惊喜，但一切尽在掌握"
        }
      ],
      "nextActId": "act-6"
    },
    {
      "id": "act-6",
      "title": "铭文铸造",
      "isKeyAct": false,
      "sceneDescription": "矛盾与争执不可避免地爆发了。将商王的命令铸刻在青铜器上双方各执一词，气氛剑拔弩张，你必须审慎应对。你作为殷商铸铜匠，深知此刻的重要性，不由得打起十二分精神。",
      "npcDialogues": [
        {
          "speaker": "长者",
          "text": "此诗明明是我先作的！",
          "avatar": "长"
        },
        {
          "speaker": "友人",
          "text": "有何凭证？",
          "avatar": "人"
        }
      ],
      "dialogues": [
        {
          "id": "d-6-1",
          "text": "审慎评估形势",
          "speaker": "你",
          "avatar": "你",
          "score": 90,
          "triggeredEvent": "铭文铸造进展顺利",
          "historicalNote": "殷商铸铜匠在这一时期的生活与经历相关的考古发现与文献记载为后人了解这一时期提供了宝贵的资料。",
          "consequence": "事情发展顺利，达成了预期目标，获得了积极的成果"
        },
        {
          "id": "d-6-2",
          "text": "勇敢开拓新路",
          "speaker": "你",
          "avatar": "你",
          "score": 60,
          "triggeredEvent": "铭文铸造遇到波折",
          "historicalNote": "殷商铸铜匠在这一时期的生活与经历相关的考古发现与文献记载为后人了解这一时期提供了宝贵的资料。",
          "consequence": "遇到了一些意料之外的困难，需要调整策略继续前进"
        },
        {
          "id": "d-6-3",
          "text": "联络同行合作",
          "speaker": "你",
          "avatar": "你",
          "score": 75,
          "triggeredEvent": "铭文铸造取得进展",
          "historicalNote": "殷商铸铜匠在这一时期的生活与经历相关的考古发现与文献记载为后人了解这一时期提供了宝贵的资料。",
          "consequence": "取得了阶段性的进展，整体形势向好发展"
        },
        {
          "id": "d-6-4",
          "text": "含蓄委婉表达",
          "speaker": "你",
          "avatar": "你",
          "score": 55,
          "triggeredEvent": "铭文铸造遭遇困境",
          "historicalNote": "殷商铸铜匠在这一时期的生活与经历相关的考古发现与文献记载为后人了解这一时期提供了宝贵的资料。",
          "consequence": "遭遇了挫折，损失有限，仍有挽回的余地"
        },
        {
          "id": "d-6-5",
          "text": "开创独特风格",
          "speaker": "你",
          "avatar": "你",
          "score": 85,
          "triggeredEvent": "铭文铸造获得突破",
          "historicalNote": "殷商铸铜匠在这一时期的生活与经历相关的考古发现与文献记载为后人了解这一时期提供了宝贵的资料。",
          "consequence": "获得了超出预期的突破性进展，令人振奋"
        },
        {
          "id": "d-6-6",
          "text": "不为利益所动",
          "speaker": "你",
          "avatar": "你",
          "score": 70,
          "triggeredEvent": "铭文铸造平稳推进",
          "historicalNote": "殷商铸铜匠在这一时期的生活与经历相关的考古发现与文献记载为后人了解这一时期提供了宝贵的资料。",
          "consequence": "稳步推进，虽无重大惊喜，但一切尽在掌握"
        }
      ],
      "nextActId": "act-7"
    },
    {
      "id": "act-7",
      "title": "祭祀大典",
      "isKeyAct": false,
      "sceneDescription": "时光流转，季节更迭。青铜礼器在重大祭祀中被使用你回顾这段时间的点点滴滴，心中充满了复杂的情感。你作为殷商铸铜匠，深知此刻的重要性，不由得打起十二分精神。",
      "npcDialogues": [
        {
          "speaker": "邻居",
          "text": "读万卷书，行万里路。",
          "avatar": "邻"
        },
        {
          "speaker": "同伴",
          "text": "你这人生，精彩得很。",
          "avatar": "友"
        }
      ],
      "dialogues": [
        {
          "id": "d-7-1",
          "text": "详查资料考究",
          "speaker": "你",
          "avatar": "你",
          "score": 90,
          "triggeredEvent": "祭祀大典进展顺利",
          "historicalNote": "该时代的政治、经济与文化背景相关的考古发现与文献记载为后人了解这一时期提供了宝贵的资料。",
          "consequence": "事情发展顺利，达成了预期目标，获得了积极的成果"
        },
        {
          "id": "d-7-2",
          "text": "大胆挥毫创作",
          "speaker": "你",
          "avatar": "你",
          "score": 60,
          "triggeredEvent": "祭祀大典遇到波折",
          "historicalNote": "该时代的政治、经济与文化背景相关的考古发现与文献记载为后人了解这一时期提供了宝贵的资料。",
          "consequence": "遇到了一些意料之外的困难，需要调整策略继续前进"
        },
        {
          "id": "d-7-3",
          "text": "与友人切磋琢磨",
          "speaker": "你",
          "avatar": "你",
          "score": 75,
          "triggeredEvent": "祭祀大典取得进展",
          "historicalNote": "该时代的政治、经济与文化背景相关的考古发现与文献记载为后人了解这一时期提供了宝贵的资料。",
          "consequence": "取得了阶段性的进展，整体形势向好发展"
        },
        {
          "id": "d-7-4",
          "text": "低调行事避险",
          "speaker": "你",
          "avatar": "你",
          "score": 55,
          "triggeredEvent": "祭祀大典遭遇困境",
          "historicalNote": "该时代的政治、经济与文化背景相关的考古发现与文献记载为后人了解这一时期提供了宝贵的资料。",
          "consequence": "遭遇了挫折，损失有限，仍有挽回的余地"
        },
        {
          "id": "d-7-5",
          "text": "另辟蹊径创新",
          "speaker": "你",
          "avatar": "你",
          "score": 85,
          "triggeredEvent": "祭祀大典获得突破",
          "historicalNote": "该时代的政治、经济与文化背景相关的考古发现与文献记载为后人了解这一时期提供了宝贵的资料。",
          "consequence": "获得了超出预期的突破性进展，令人振奋"
        },
        {
          "id": "d-7-6",
          "text": "坚守气节原则",
          "speaker": "你",
          "avatar": "你",
          "score": 70,
          "triggeredEvent": "祭祀大典平稳推进",
          "historicalNote": "该时代的政治、经济与文化背景相关的考古发现与文献记载为后人了解这一时期提供了宝贵的资料。",
          "consequence": "稳步推进，虽无重大惊喜，但一切尽在掌握"
        }
      ],
      "nextActId": "act-8"
    },
    {
      "id": "act-8",
      "title": "王朝覆灭",
      "isKeyAct": true,
      "sceneDescription": "故事接近尾声，而你的旅程仍在继续。殷商覆灭后铸铜技术流传到周人手中这段经历将永远铭刻在你的记忆中，成为生命的一部分。你作为殷商铸铜匠，深知此刻的重要性，不由得打起十二分精神。",
      "npcDialogues": [
        {
          "speaker": "友人",
          "text": "这首诗还得再斟酌斟酌。",
          "avatar": "人"
        },
        {
          "speaker": "长者",
          "text": "腹稿都有了，就缺个好题目。",
          "avatar": "长"
        }
      ],
      "dialogues": [
        {
          "id": "d-8-1",
          "text": "多方打听确认",
          "speaker": "你",
          "avatar": "你",
          "score": 90,
          "triggeredEvent": "王朝覆灭进展顺利",
          "historicalNote": "历史对后世的深远影响相关的考古发现与文献记载为后人了解这一时期提供了宝贵的资料。",
          "consequence": "事情发展顺利，达成了预期目标，获得了积极的成果"
        },
        {
          "id": "d-8-2",
          "text": "果断投资决策",
          "speaker": "你",
          "avatar": "你",
          "score": 60,
          "triggeredEvent": "王朝覆灭遇到波折",
          "historicalNote": "历史对后世的深远影响相关的考古发现与文献记载为后人了解这一时期提供了宝贵的资料。",
          "consequence": "遇到了一些意料之外的困难，需要调整策略继续前进"
        },
        {
          "id": "d-8-3",
          "text": "寻求师长指点",
          "speaker": "你",
          "avatar": "你",
          "score": 75,
          "triggeredEvent": "王朝覆灭取得进展",
          "historicalNote": "历史对后世的深远影响相关的考古发现与文献记载为后人了解这一时期提供了宝贵的资料。",
          "consequence": "取得了阶段性的进展，整体形势向好发展"
        },
        {
          "id": "d-8-4",
          "text": "稳扎稳打经营",
          "speaker": "你",
          "avatar": "你",
          "score": 55,
          "triggeredEvent": "王朝覆灭遭遇困境",
          "historicalNote": "历史对后世的深远影响相关的考古发现与文献记载为后人了解这一时期提供了宝贵的资料。",
          "consequence": "遭遇了挫折，损失有限，仍有挽回的余地"
        },
        {
          "id": "d-8-5",
          "text": "改良经营方式",
          "speaker": "你",
          "avatar": "你",
          "score": 85,
          "triggeredEvent": "王朝覆灭获得突破",
          "historicalNote": "历史对后世的深远影响相关的考古发现与文献记载为后人了解这一时期提供了宝贵的资料。",
          "consequence": "获得了超出预期的突破性进展，令人振奋"
        },
        {
          "id": "d-8-6",
          "text": "诚信童叟无欺",
          "speaker": "你",
          "avatar": "你",
          "score": 70,
          "triggeredEvent": "王朝覆灭平稳推进",
          "historicalNote": "历史对后世的深远影响相关的考古发现与文献记载为后人了解这一时期提供了宝贵的资料。",
          "consequence": "稳步推进，虽无重大惊喜，但一切尽在掌握"
        }
      ]
    }
  ]
}